c4m/arrakeen/__init__.py
c4m_arrakeen-25.2a1.dist-info/METADATA
c4m_arrakeen-25.2a1.dist-info/WHEEL
c4m_arrakeen-25.2a1.dist-info/entry_points.txt
c4m_arrakeen-25.2a1.dist-info/licenses/LICENSE.md
c4m_arrakeen-25.2a1.dist-info/licenses/LICENSE_rationale.md
c4m_arrakeen-25.2a1.dist-info/RECORD
