Metadata-Version: 2.1
Name: c4m-arrakeen
Version: 25.2a1
Summary: Project Arrakeen, python framework for portable PDKs for digital and analog design.
Author: Chips4Makers contributors
License: AGPL-3.0-or-later OR GPL-2.0-or-later OR CERN-OHL-S-2.0+ OR Apache-2.0
Requires-Python: >=3.8
Requires-Dist: PDKMaster==0.11.5
Requires-Dist: pdkmaster-io-klayout==0.1.6
Requires-Dist: c4m-flexcell==0.4.5
Requires-Dist: c4m-flexio==0.4.8
Requires-Dist: c4m-pdk-sky130==0.2.6
Requires-Dist: c4m-pdk-gf180mcu==0.0.10
Requires-Dist: c4m-pdk-ihpsg13g2==0.1.2
